clickuphelper/__init__.py
clickuphelper/cli.py
clickuphelper-0.3.9.dist-info/LICENSE
clickuphelper-0.3.9.dist-info/METADATA
clickuphelper-0.3.9.dist-info/WHEEL
clickuphelper-0.3.9.dist-info/entry_points.txt
clickuphelper-0.3.9.dist-info/top_level.txt
clickuphelper-0.3.9.dist-info/RECORD
