Metadata-Version: 2.1
Name: clickuphelper
Version: 0.3.9
Summary: Python classes, cli, and tooling to interact with Clickup
Home-page: https://github.com/newmanrs/clickuphelper
Author: Richmond Newman
Author-email: Robert Newman <newmanrs@example.com>
License: MIT License
Project-URL: Homepage, https://github.com/newmanrs/clickuphelper
Project-URL: Bug Tracker, https://github.com/newmanrs/clickuphelper/issues
Keywords: clickup,api,cli,task management
Classifier: License :: OSI Approved :: MIT License
Classifier: Programming Language :: Python
Classifier: Programming Language :: Python :: 3
Classifier: Topic :: Software Development :: Libraries :: Python Modules
Classifier: Topic :: Utilities
Requires-Python: >=3.6
License-File: LICENSE
Requires-Dist: click
Requires-Dist: requests
Provides-Extra: dev
Requires-Dist: pytest; extra == "dev"
